Fuzz_output/__init__.py
Fuzz_output/main.py
Fuzz_Output_EVAMortus-0.0.1.dist-info/LICENSE
Fuzz_Output_EVAMortus-0.0.1.dist-info/METADATA
Fuzz_Output_EVAMortus-0.0.1.dist-info/WHEEL
Fuzz_Output_EVAMortus-0.0.1.dist-info/top_level.txt
Fuzz_Output_EVAMortus-0.0.1.dist-info/RECORD
